README.md
setup.py
melopero_RV_3028/RV_3028.py
melopero_RV_3028/__init__.py
melopero_RV_3028.egg-info/PKG-INFO
melopero_RV_3028.egg-info/SOURCES.txt
melopero_RV_3028.egg-info/dependency_links.txt
melopero_RV_3028.egg-info/requires.txt
melopero_RV_3028.egg-info/top_level.txt