Metadata-Version: 1.0
Name: melopero-RV-3028
Version: 0.1.1
Summary: A module to easily access the RV-3028 rtc features.
Home-page: https://github.com/melopero/Melopero_RV-3028
Author: Leonardo La Rocca
Author-email: info@melopero.com
License: MIT
Platform: UNKNOWN
